icemac.truncatetext-1.1.1-py2.7-nspkg.pth
icemac/truncatetext/README.rst
icemac/truncatetext/__init__.py
icemac/truncatetext/tests.py
icemac.truncatetext-1.1.1.dist-info/DESCRIPTION.rst
icemac.truncatetext-1.1.1.dist-info/METADATA
icemac.truncatetext-1.1.1.dist-info/RECORD
icemac.truncatetext-1.1.1.dist-info/WHEEL
icemac.truncatetext-1.1.1.dist-info/metadata.json
icemac.truncatetext-1.1.1.dist-info/namespace_packages.txt
icemac.truncatetext-1.1.1.dist-info/top_level.txt
icemac.truncatetext-1.1.1.dist-info/zip-safe
